neuroglia/__init__.py
neuroglia/a2a/__init__.py
neuroglia/a2a/protocol.py
neuroglia/application/__init__.py
neuroglia/application/background_scheduler.py
neuroglia/coordination/__init__.py
neuroglia/coordination/abstractions.py
neuroglia/coordination/leader_election.py
neuroglia/coordination/redis_backend.py
neuroglia/core/__init__.py
neuroglia/core/module_loader.py
neuroglia/core/operation_result.py
neuroglia/core/problem_details.py
neuroglia/core/type_extensions.py
neuroglia/core/type_finder.py
neuroglia/core/type_registry.py
neuroglia/data/__init__.py
neuroglia/data/abstractions.py
neuroglia/data/agent/__init__.py
neuroglia/data/agent/agent_events.py
neuroglia/data/agent/agent_state.py
neuroglia/data/conversation/__init__.py
neuroglia/data/conversation/execution_context.py
neuroglia/data/conversation/message.py
neuroglia/data/conversation/session.py
neuroglia/data/conversation/tool_call.py
neuroglia/data/exceptions.py
neuroglia/data/infrastructure/__init__.py
neuroglia/data/infrastructure/abstractions.py
neuroglia/data/infrastructure/event_sourcing/__init__.py
neuroglia/data/infrastructure/event_sourcing/abstractions.py
neuroglia/data/infrastructure/event_sourcing/event_sourcing_repository.py
neuroglia/data/infrastructure/event_sourcing/event_store/__init__.py
neuroglia/data/infrastructure/event_sourcing/event_store/event_store.py
neuroglia/data/infrastructure/event_sourcing/read_model_reconciliator.py
neuroglia/data/infrastructure/filesystem/__init__.py
neuroglia/data/infrastructure/filesystem/filesystem_repository.py
neuroglia/data/infrastructure/memory/__init__.py
neuroglia/data/infrastructure/memory/memory_repository.py
neuroglia/data/infrastructure/mongo/__init__.py
neuroglia/data/infrastructure/mongo/enhanced_mongo_repository.py
neuroglia/data/infrastructure/mongo/mongo_repository.py
neuroglia/data/infrastructure/mongo/motor_query.py
neuroglia/data/infrastructure/mongo/motor_repository.py
neuroglia/data/infrastructure/mongo/serialization_helper.py
neuroglia_python-0.9.0.dist-info/METADATA
neuroglia_python-0.9.0.dist-info/WHEEL
neuroglia_python-0.9.0.dist-info/licenses/LICENSE
neuroglia_python-0.9.0.dist-info/RECORD
