Metadata-Version: 2.4
Name: neuroglia-python
Version: 0.9.0
Summary: Port from .NET to Python of the Neuroglia Framework
License: Apache
License-File: LICENSE
Author: Charles d'Avernas
Author-email: charles.davernas@neuroglia.io
Requires-Python: >=3.9,<4.0
Classifier: License :: Other/Proprietary License
Classifier: Programming Language :: Python :: 3
Classifier: Programming Language :: Python :: 3.9
Classifier: Programming Language :: Python :: 3.10
Classifier: Programming Language :: Python :: 3.11
Classifier: Programming Language :: Python :: 3.12
Classifier: Programming Language :: Python :: 3.13
Classifier: Programming Language :: Python :: 3.14
Provides-Extra: all
Provides-Extra: aws
Provides-Extra: etcd
Provides-Extra: eventstore
Provides-Extra: mongodb
Provides-Extra: redis
Requires-Dist: annotated-types (==0.7.0)
Requires-Dist: apscheduler (==3.11.0)
Requires-Dist: boto3 (==1.40.64) ; extra == "aws" or extra == "all"
Requires-Dist: classy-fastapi (==0.6.1)
Requires-Dist: email-validator (==2.2.0)
Requires-Dist: etcd3-py (==0.1.6) ; extra == "etcd" or extra == "all"
Requires-Dist: fastapi (==0.115.5)
Requires-Dist: grpcio (==1.76.0)
Requires-Dist: h11 (==0.16.0)
Requires-Dist: httpx (==0.27.2)
Requires-Dist: itsdangerous (==2.2.0)
Requires-Dist: jinja2 (==3.1.4)
Requires-Dist: kurrentdbclient (==1.1.2) ; extra == "eventstore" or extra == "all"
Requires-Dist: motor (==3.7.0) ; extra == "mongodb" or extra == "all"
Requires-Dist: multipledispatch (==1.0.0)
Requires-Dist: opentelemetry-api (==1.38.0)
Requires-Dist: opentelemetry-exporter-otlp-proto-grpc (==1.38.0)
Requires-Dist: opentelemetry-exporter-otlp-proto-http (==1.38.0)
Requires-Dist: opentelemetry-exporter-prometheus (==0.59b0)
Requires-Dist: opentelemetry-instrumentation (==0.59b0)
Requires-Dist: opentelemetry-instrumentation-fastapi (==0.59b0)
Requires-Dist: opentelemetry-instrumentation-httpx (==0.59b0)
Requires-Dist: opentelemetry-instrumentation-logging (==0.59b0)
Requires-Dist: opentelemetry-instrumentation-system-metrics (==0.59b0)
Requires-Dist: opentelemetry-sdk (==1.38.0)
Requires-Dist: passlib[bcrypt] (==1.7.4)
Requires-Dist: prometheus-client (==0.21.0)
Requires-Dist: protobuf (==6.33.1) ; extra == "etcd" or extra == "all"
Requires-Dist: pydantic-settings (==2.6.1)
Requires-Dist: pydantic[email] (==2.11.0)
Requires-Dist: pyjwt (==2.10.1)
Requires-Dist: pymongo (==4.15.4) ; extra == "mongodb" or extra == "all"
Requires-Dist: python-dotenv (==1.0.1)
Requires-Dist: python-multipart (==0.0.17)
Requires-Dist: redis (==5.2.0) ; extra == "redis" or extra == "all"
Requires-Dist: rx (==3.2.0)
Requires-Dist: typing-extensions (==4.12.2)
Requires-Dist: uvicorn (==0.35.0)
